[
  {
  "numero": 1,
  "question": "Which blood component is primarily responsible for oxygen transport?",
  "options": [
    "Platelets",
    "White blood cells",
    "Red blood cells (erythrocytes)",
    "Plasma"
  ],
  "answer": "Red blood cells (erythrocytes)"
},
{
  "numero": 2,
  "question": "What is the main symptom of anemia?",
  "options": [
    "Fever",
    "Fatigue and pallor",
    "Chest pain",
    "Swollen lymph nodes"
  ],
  "answer": "Fatigue and pallor"
},
{
  "numero": 3,
  "question": "Which blood test measures the percentage of red blood cells in the total blood volume?",
  "options": [
    "White blood cell count",
    "Hematocrit",
    "Platelet count",
    "Bleeding time"
  ],
  "answer": "Hematocrit"
},
{
  "numero": 4,
  "question": "Acute myeloid leukemia (AML) is a disease characterized by:",
  "options": [
    "A bacterial infection of the blood",
    "Rapid proliferation of immature myeloid cells",
    "Vitamin B12 deficiency",
    "Increased platelets"
  ],
  "answer": "Rapid proliferation of immature myeloid cells"
},
{
  "numero": 5,
  "question": "Which factor is essential for blood clotting?",
  "options": [
    "Erythropoietin",
    "Fibrinogen",
    "Hemoglobin",
    "Globulin"
  ],
  "answer": "Fibrinogen"
},
{
  "numero": 6,
  "question": "What is the most common cause of iron deficiency anemia?",
  "options": [
    "Chronic hemorrhage",
    "Infection",
    "Iron deficiency",
    "Autoimmune disease"
  ],
  "answer": "Iron deficiency"
},
{
  "numero": 7,
  "question": "Which test is used to diagnose thrombocytopenia?",
  "options": [
    "Red blood cell count",
    "Platelet count",
    "Hematocrit",
    "Erythrocyte sedimentation rate"
  ],
  "answer": "Platelet count"
},
{
  "numero": 8,
  "question": "Sickle cell disease is due to:",
  "options": [
    "Iron deficiency",
    "Bacterial infection",
    "A genetic mutation of hemoglobin",
    "Vitamin B12 deficiency"
  ],
  "answer": "A genetic mutation of hemoglobin"
},
{
  "numero": 9,
  "question": "Which medication is used to prevent blood clot formation?",
  "options": [
    "Antibiotics",
    "Anticoagulants (heparin, warfarin)",
    "Anti-inflammatories",
    "Corticosteroids"
  ],
  "answer": "Anticoagulants (heparin, warfarin)"
},
{
  "numero": 10,
  "question": "What is the main role of platelets in the blood?",
  "options": [
    "Transport oxygen",
    "Fight infections",
    "Participate in coagulation",
    "Regulate blood pressure"
  ],
  "answer": "Participate in coagulation"
},
{
  "numero": 11,
  "question": "Which test is used to measure blood clotting time?",
  "options": [
    "White blood cell count",
    "Hemoglobin",
    "Prothrombin time (PT) and activated partial thromboplastin time (aPTT)",
    "Blood glucose"
  ],
  "answer": "Prothrombin time (PT) and activated partial thromboplastin time (aPTT)"
},
{
  "numero": 12,
  "question": "Hodgkin's disease is a cancer of the:",
  "options": [
    "Liver",
    "Lungs",
    "Lymphatic system",
    "Bones"
  ],
  "answer": "Lymphatic system"
},
{
  "numero": 13,
  "question": "What is the role of erythropoietin?",
  "options": [
    "Coagulation",
    "Stimulation of red blood cell production",
    "Immune response",
    "Nutrient transport"
  ],
  "answer": "Stimulation of red blood cell production"
},
{
  "numero": 14,
  "question": "Which type of anemia is caused by vitamin B12 deficiency?",
  "options": [
    "Iron deficiency anemia",
    "Aplastic anemia",
    "Megaloblastic anemia",
    "Hemolytic anemia"
  ],
  "answer": "Megaloblastic anemia"
},
{
  "numero": 15,
  "question": "Which test evaluates bone marrow function?",
  "options": [
    "X-ray",
    "Myelogram (bone marrow aspiration)",
    "Abdominal ultrasound",
    "Brain CT scan"
  ],
  "answer": "Myelogram (bone marrow aspiration)"
},
{
  "numero": 16,
  "question": "Which cell is mainly affected in acute lymphoblastic leukemia (ALL)?",
  "options": [
    "Red blood cells",
    "Platelets",
    "Immature lymphocytes",
    "Neutrophils"
  ],
  "answer": "Immature lymphocytes"
},
{
  "numero": 17,
  "question": "What is the main treatment for iron deficiency anemia?",
  "options": [
    "Antibiotics",
    "Iron supplementation",
    "Corticosteroids",
    "Anticoagulants"
  ],
  "answer": "Iron supplementation"
},
{
  "numero": 18,
  "question": "What is the major complication of severe thrombocytopenia?",
  "options": [
    "Infection",
    "High risk of bleeding",
    "Joint pain",
    "Fatigue"
  ],
  "answer": "High risk of bleeding"
},
{
  "numero": 19,
  "question": "What is the characteristic sign of polycythemia?",
  "options": [
    "Anemia",
    "Thrombocytopenia",
    "Abnormally increased number of red blood cells",
    "Leukopenia"
  ],
  "answer": "Abnormally increased number of red blood cells"
},
{
  "numero": 20,
  "question": "Which blood test assesses kidney function related to hematology?",
  "options": [
    "Hemoglobin",
    "Platelet count",
    "Creatinine level",
    "Erythrocyte sedimentation rate"
  ],
  "answer": "Creatinine level"
}
,{
  "numero": 21,
  "question": "Which type of white blood cell is primarily responsible for defending against bacterial infections?",
  "options": ["Lymphocytes", "Erythrocytes", "Neutrophils", "Monocytes"],
  "answer": "Neutrophils"
},
{
  "numero": 22,
  "question": "What is the main symptom of chronic myeloid leukemia (CML)?",
  "options": ["High fever", "Acute bone pain", "Fatigue, splenomegaly", "Swollen lymph nodes"],
  "answer": "Fatigue, splenomegaly"
},
{
  "numero": 23,
  "question": "Sickle cell disease causes:",
  "options": ["Hypercoagulation", "Bacterial infection", "Hemolytic anemia due to abnormal red blood cell shape", "Iron deficiency"],
  "answer": "Hemolytic anemia due to abnormal red blood cell shape"
},
{
  "numero": 24,
  "question": "What is the role of blood plasma?",
  "options": [
    "Transport only red blood cells",
    "Transport nutrients, hormones, waste products, and clotting components",
    "Produce white blood cells",
    "Regulate body temperature"
  ],
  "answer": "Transport nutrients, hormones, waste products, and clotting components"
},
{
  "numero": 25,
  "question": "What is the main cause of aplastic anemia?",
  "options": [
    "Iron deficiency",
    "Bacterial infection",
    "Bone marrow failure (reduced production of blood cells)",
    "Genetic mutation"
  ],
  "answer": "Bone marrow failure (reduced production of blood cells)"
},
{
  "numero": 26,
  "question": "Which blood test detects hemolysis?",
  "options": [
    "White blood cell count",
    "Clotting time",
    "Bilirubin and lactate dehydrogenase (LDH) levels",
    "Blood glucose"
  ],
  "answer": "Bilirubin and lactate dehydrogenase (LDH) levels"
},
{
  "numero": 27,
  "question": "What treatment is used for acute leukemia?",
  "options": ["Antibiotics", "Chemotherapy", "Corticosteroids only", "Anticoagulants"],
  "answer": "Chemotherapy"
},
{
  "numero": 28,
  "question": "Which factor can cause deep vein thrombosis (DVT)?",
  "options": [
    "Low blood pressure",
    "Prolonged immobilization",
    "Iron deficiency anemia",
    "Viral infection"
  ],
  "answer": "Prolonged immobilization"
},
{
  "numero": 29,
  "question": "What is the role of B lymphocytes?",
  "options": [
    "Phagocytosis",
    "Antibody production",
    "Blood clotting",
    "Oxygen transport"
  ],
  "answer": "Antibody production"
},
{
  "numero": 30,
  "question": "Which test is used to detect hemophilia?",
  "options": [
    "Platelet count",
    "Hematocrit",
    "Prolonged clotting time (PT, aPTT)",
    "Creatinine level"
  ],
  "answer": "Prolonged clotting time (PT, aPTT)"
},{
  "numero": 31,
  "question": "What is the main symptom of hemolytic anemia?",
  "options": ["Fever only", "Joint pain", "Jaundice, fatigue, splenomegaly", "Swollen lymph nodes"],
  "answer": "Jaundice, fatigue, splenomegaly"
},
{
  "numero": 32,
  "question": "What is the first-line treatment for megaloblastic anemia?",
  "options": ["Iron supplementation", "Vitamin B12 or folic acid", "Antibiotics", "Corticosteroids"],
  "answer": "Vitamin B12 or folic acid"
},
{
  "numero": 33,
  "question": "What is the most common infectious agent responsible for infectious anemia?",
  "options": ["Influenza virus", "Plasmodium (malaria)", "Gram-negative bacteria", "Fungi"],
  "answer": "Plasmodium (malaria)"
},
{
  "numero": 34,
  "question": "What is the role of platelets in tissue repair?",
  "options": ["Transport oxygen", "Produce antibodies", "Form a platelet plug to stop bleeding", "Fight infection"],
  "answer": "Form a platelet plug to stop bleeding"
},
{
  "numero": 35,
  "question": "Which test is used to diagnose leukemia?",
  "options": ["Chest X-ray", "Myelogram and blood count", "Abdominal CT scan", "Echocardiography"],
  "answer": "Myelogram and blood count"
},
{
  "numero": 36,
  "question": "What is the main symptom of thrombocytosis?",
  "options": ["Fatigue", "Anemia", "Increased risk of thrombosis", "Fever"],
  "answer": "Increased risk of thrombosis"
},
{
  "numero": 37,
  "question": "What is the main risk factor for thrombocytopenia?",
  "options": ["Hypercholesterolemia", "Hypotension", "Bleeding and hemorrhage", "Hyperglycemia"],
  "answer": "Bleeding and hemorrhage"
},
{
  "numero": 38,
  "question": "What treatment is used for sickle cell disease?",
  "options": ["Antibiotics only", "Anticoagulants", "Hydroxyurea and blood transfusions", "Corticosteroids"],
  "answer": "Hydroxyurea and blood transfusions"
},
{
  "numero": 39,
  "question": "What is the role of hemoglobin?",
  "options": ["Coagulation", "Immunity", "Oxygen transport", "Nutrient transport"],
  "answer": "Oxygen transport"
},
{
  "numero": 40,
  "question": "What is the clinical sign of anemia?",
  "options": ["Hyperpigmentation", "Paleness of skin and mucous membranes", "Cyanosis", "Edema"],
  "answer": "Paleness of skin and mucous membranes"
},
{
  "numero": 41,
  "question": "Which type of white blood cells is mainly involved in the humoral immune response?",
  "options": ["Neutrophils", "B lymphocytes", "Monocytes", "Eosinophils"],
  "answer": "B lymphocytes"
},
{
  "numero": 42,
  "question": "What is the main role of neutrophils?",
  "options": ["Oxygen transport", "Antibody production", "Phagocytosis of bacteria", "Coagulation"],
  "answer": "Phagocytosis of bacteria"
},
{
  "numero": 43,
  "question": "Which test is used to screen for coagulation disorders?",
  "options": ["Platelet count only", "Hemoglobin", "Prothrombin time (PT) and activated partial thromboplastin time (aPTT)", "Blood glucose"],
  "answer": "Prothrombin time (PT) and activated partial thromboplastin time (aPTT)"
},
{
  "numero": 44,
  "question": "What is the treatment for hemophilia A?",
  "options": ["Antibiotics", "Corticosteroids", "Factor VIII injection", "Anticoagulants"],
  "answer": "Factor VIII injection"
},
{
  "numero": 45,
  "question": "What is the characteristic sign of leukemia?",
  "options": ["Chest pain", "Paleness only", "Fatigue, frequent infections, bleeding", "Abdominal pain"],
  "answer": "Fatigue, frequent infections, bleeding"
},
{
  "numero": 46,
  "question": "Which blood cell is responsible for allergic reactions?",
  "options": ["Neutrophils", "Eosinophils", "Monocytes", "Lymphocytes"],
  "answer": "Eosinophils"
},
{
  "numero": 47,
  "question": "What is the role of monocytes?",
  "options": ["Antibody production", "Oxygen transport", "Phagocytosis and antigen presentation", "Coagulation"],
  "answer": "Phagocytosis and antigen presentation"
},
{
  "numero": 48,
  "question": "What is the most common cause of bleeding in a patient with thrombocytopenia?",
  "options": ["Infection", "Hypercoagulability", "Decreased platelet count", "Iron deficiency anemia"],
  "answer": "Decreased platelet count"
},
{
  "numero": 49,
  "question": "What is the role of factor VIII?",
  "options": ["Transport oxygen", "Antibody production", "Blood coagulation (intrinsic pathway)", "Immune response"],
  "answer": "Blood coagulation (intrinsic pathway)"
},
{
  "numero": 50,
  "question": "What is the main treatment for acute lymphoblastic leukemia (ALL)?",
  "options": ["Antibiotics", "Intensive chemotherapy", "Iron supplementation", "Anticoagulants"],
  "answer": "Intensive chemotherapy"
}
]
